src/divider.v
// Nicholas West, 2024
/*
	* This file creates the divider we use for calculating the modulus in our mersenne prime trial factoring
	* It uses the standard shift and subtract algorithm, modified to enable arbitrary bit widths
*/

`default_nettype none

module divider #(
		parameter BITWIDTH=32
	) (
	input wire sys_clk,
	input wire sys_rst_n,
	input wire start,
	input wire [BITWIDTH - 1:0] numerator,
	input wire [BITWIDTH - 1:0] denominator, 
	output reg [BITWIDTH - 1:0] remainder,
	output wire finished
	);

	// Despite calling this a divider its more of a modulo since we never return the quotient

	parameter WAIT = 1'b0;
	parameter DIVIDE = 1'b1;

	reg [BITWIDTH - 1:0] dividend;
	reg [BITWIDTH - 1:0] divisor;
	wire [BITWIDTH - 1:0] nextRemainder;

	reg state;
	// Minimum bit width to store value from 0 to BITWIDTH
	reg [$clog2(BITWIDTH) - 1:0] count;

	assign finished = ~state;
	assign nextRemainder = {remainder, dividend[count]};
	
	always @(posedge sys_clk) begin
		if (start) begin // Initialize everything to starting values
			state <= DIVIDE;
			count <= BITWIDTH - 1;
			dividend <= numerator;
			divisor <= denominator;
			remainder <= 0;
		end
		if (state == DIVIDE) begin // Simple shift and subtract division algorithm
			// No matter if divisor can fit in remainder, add in the next bit of dividend
			// If it does happen to fit, subtract (this is where we would add a 1 to the quotient but we dont need that)
			if (nextRemainder >= divisor) begin
				remainder <= nextRemainder - divisor;
			end else begin
				remainder <= nextRemainder;
			end

			// End case
			if (count == 0) begin
				state <= WAIT;
			end

			count <= count - 1;
		end
	end

endmodule


module pipelinedDivider #(
	parameter BITWIDTH=32,
	parameter MEMWIDTH = 10 // it width of memory addresses, reading always in bytes
	) (
	input wire sys_clk,
	input wire sys_rst_n,
	input wire start,
	input wire [127:0] numerator,
	input wire [127:0] denominator, 
	output reg [127:0] remainder,
	output wire finished
	);

	// Despite calling this a divider its more of a modulo since we never return the quotient

	parameter WAIT = 2'b00;
	parameter DIVIDE = 2'b01;
	parameter SUBTRACT = 2'b10;
	parameter COMPARE = 2'b11;

	// The intent is to replace these with seperate SRAM or memory at some point
	reg [127:0] fullDividend;
	reg [127:0] fullDivisor;
	wire [127:0] nextRemainder;

	reg [BITWIDTH - 1:0] workingDividend;
	reg [BITWIDTH - 1:0] workingDivisor;

	reg [1:0] state;
	// Minimum bit width to store value from 0 to BITWIDTH
	reg [$clog2(127) - 1:0] count;

	assign finished = ~state;
	assign nextRemainder = {remainder, fullDividend[count]};
	
	always @(posedge sys_clk) begin
		if (start) begin // Initialize everything to starting values
			state <= DIVIDE;
			count <= BITWIDTH - 1;
			dividend <= numerator;
			divisor <= denominator;
			remainder <= 0;
		end
		if (state == DIVIDE) begin // Simple shift and subtract division algorithm
			// No matter if divisor can fit in remainder, add in the next bit of dividend
			// If it does happen to fit, subtract (this is where we would add a 1 to the quotient but we dont need that)
			if (nextRemainder >= divisor) begin
				remainder <= nextRemainder - divisor;
			end else begin
				remainder <= nextRemainder;
			end

			// End case
			if (count == 0) begin
				state <= WAIT;
			end

			count <= count - 1;
		end
	end
	
endmodule

test/tb.v
`default_nettype none
`timescale 1ns / 1ps

module tb();

	// If this is commented out in the repo it's because I don't want a terrabyte of VCD garbage
	/*
	initial begin
		$dumpfile("tb.vcd");
		$dumpvars(0, tb);
	end
	*/

	// instantiate our divider!
	reg clk;
	reg rst_n;
	reg start;
	reg [31:0] dividend;
	reg [31:0] divisor;
	wire [31:0] remainder;
	wire data_ready;

	divider modCalculator(
		.sys_clk(clk),
		.sys_rst_n(rst_n),
		.start(start),
		.numerator(dividend),
		.denominator(divisor),
		.remainder(remainder),
		.finished(data_ready)
	);

endmodule

test/tb.vcd
$date
	Sat Dec  7 23:18:38 2024
$end
$version
	Icarus Verilog
$end
$timescale
	1ps
$end
$scope module tb $end
$var wire 32 ! remainder [31:0] $end
$var wire 1 " data_ready $end
$var reg 1 # clk $end
$var reg 32 $ dividend [31:0] $end
$var reg 32 % divisor [31:0] $end
$var reg 1 & rst_n $end
$var reg 1 ' start $end
$scope module modCalculator $end
$var wire 32 ( denominator [31:0] $end
$var wire 1 " finished $end
$var wire 32 ) numerator [31:0] $end
$var wire 1 ' start $end
$var wire 1 # sys_clk $end
$var wire 1 & sys_rst_n $end
$var wire 32 * nextRemainder [31:0] $end
$var reg 5 + count [4:0] $end
$var reg 32 , dividend [31:0] $end
$var reg 32 - divisor [31:0] $end
$var reg 32 . remainder [31:0] $end
$var reg 1 / state $end
$upscope $end
$upscope $end
$enddefinitions $end
#0
$dumpvars
x/
bx .
bx -
bx ,
bx +
bx *
b0 )
b0 (
0'
0&
b0 %
b0 $
1#
x"
bx !
$end
#16500
0#
#33000
1#
#49500
0#
#66000
1#
#82500
0#
#99000
1#
#115500
0#
#132000
1#
#148500
0#
#165000
1#
#181500
0#
#198000
1#
#214500
0#
#231000
1#
#247500
0#
#264000
1#
#280500
0#
#297000
1'
b100 %
b100 (
b1111 $
b1111 )
1&
1#
#313500
0#
#330000
0'
b0 *
0"
b0 !
b0 .
b100 -
b1111 ,
b11111 +
1/
1#
#346500
0#
#363000
b11110 +
1#
#379500
0#
#396000
b11101 +
1#
#412500
0#
#429000
b11100 +
1#
#445500
0#
#462000
b11011 +
1#
#478500
0#
#495000
b11010 +
1#
#511500
0#
#528000
b11001 +
1#
#544500
0#
#561000
b11000 +
1#
#577500
0#
#594000
b10111 +
1#
#610500
0#
#627000
b10110 +
1#
#643500
0#
#660000
b10101 +
1#
#676500
0#
#693000
b10100 +
1#
#709500
0#
#726000
b10011 +
1#
#742500
0#
#759000
b10010 +
1#
#775500
0#
#792000
b10001 +
1#
#808500
0#
#825000
b10000 +
1#
#841500
0#
#858000
b1111 +
1#
#874500
0#
#891000
b1110 +
1#
#907500
0#
#924000
b1101 +
1#
#940500
0#
#957000
b1100 +
1#
#973500
0#
#990000
b1011 +
1#
#1006500
0#
#1023000
b1010 +
1#
#1039500
0#
#1056000
b1001 +
1#
#1072500
0#
#1089000
b1000 +
1#
#1105500
0#
#1122000
b111 +
1#
#1138500
0#
#1155000
b110 +
1#
#1171500
0#
#1188000
b101 +
1#
#1204500
0#
#1221000
b100 +
1#
#1237500
0#
#1254000
b1 *
b11 +
1#
#1270500
0#
#1287000
b11 *
b10 +
b1 !
b1 .
1#
#1303500
0#
#1320000
b111 *
b1 +
b11 !
b11 .
1#
#1336500
0#
#1353000
b0 +
1#
#1369500
0#
#1386000
b110 *
1"
b11111 +
0/
1#
#1402500
0#
#1419000
1#
#1435500
0#
#1452000
1#
#1468500
0#
#1485000
1#
#1501500
0#
#1518000
1#
#1534500
0#
#1551000
1#
#1567500
0#
#1584000
1#
#1600500
0#
#1617000
1#
#1633500
0#
#1650000
1'
b1000011011000011111011110100110 %
b1000011011000011111011110100110 (
b1111011011011100100001011011011 $
b1111011011011100100001011011011 )
1#
#1666500
0#
#1683000
0'
b0 *
0"
b0 !
b0 .
b1000011011000011111011110100110 -
b1111011011011100100001011011011 ,
1/
1#
#1699500
0#
#1716000
b1 *
b11110 +
1#
#1732500
0#
#1749000
b11 *
b11101 +
b1 !
b1 .
1#
#1765500
0#
#1782000
b111 *
b11100 +
b11 !
b11 .
1#
#1798500
0#
#1815000
b1111 *
b11011 +
b111 !
b111 .
1#
#1831500
0#
#1848000
b11110 *
b11010 +
b1111 !
b1111 .
1#
#1864500
0#
#1881000
b111101 *
b11001 +
b11110 !
b11110 .
1#
#1897500
0#
#1914000
b1111011 *
b11000 +
b111101 !
b111101 .
1#
#1930500
0#
#1947000
b11110110 *
b10111 +
b1111011 !
b1111011 .
1#
#1963500
0#
#1980000
b111101101 *
b10110 +
b11110110 !
b11110110 .
1#
#1996500
0#
#2013000
b1111011011 *
b10101 +
b111101101 !
b111101101 .
1#
#2029500
0#
#2046000
b11110110110 *
b10100 +
b1111011011 !
b1111011011 .
1#
#2062500
0#
#2079000
b111101101101 *
b10011 +
b11110110110 !
b11110110110 .
1#
#2095500
0#
#2112000
b1111011011011 *
b10010 +
b111101101101 !
b111101101101 .
1#
#2128500
0#
#2145000
b11110110110111 *
b10001 +
b1111011011011 !
b1111011011011 .
1#
#2161500
0#
#2178000
b111101101101110 *
b10000 +
b11110110110111 !
b11110110110111 .
1#
#2194500
0#
#2211000
b1111011011011100 *
b1111 +
b111101101101110 !
b111101101101110 .
1#
#2227500
0#
#2244000
b11110110110111001 *
b1110 +
b1111011011011100 !
b1111011011011100 .
1#
#2260500
0#
#2277000
b111101101101110010 *
b1101 +
b11110110110111001 !
b11110110110111001 .
1#
#2293500
0#
#2310000
b1111011011011100100 *
b1100 +
b111101101101110010 !
b111101101101110010 .
1#
#2326500
0#
#2343000
b11110110110111001000 *
b1011 +
b1111011011011100100 !
b1111011011011100100 .
1#
#2359500
0#
#2376000
b111101101101110010000 *
b1010 +
b11110110110111001000 !
b11110110110111001000 .
1#
#2392500
0#
#2409000
b1111011011011100100001 *
b1001 +
b111101101101110010000 !
b111101101101110010000 .
1#
#2425500
0#
#2442000
b11110110110111001000010 *
b1000 +
b1111011011011100100001 !
b1111011011011100100001 .
1#
#2458500
0#
#2475000
b111101101101110010000101 *
b111 +
b11110110110111001000010 !
b11110110110111001000010 .
1#
#2491500
0#
#2508000
b1111011011011100100001011 *
b110 +
b111101101101110010000101 !
b111101101101110010000101 .
1#
#2524500
0#
#2541000
b11110110110111001000010110 *
b101 +
b1111011011011100100001011 !
b1111011011011100100001011 .
1#
#2557500
0#
#2574000
b111101101101110010000101101 *
b100 +
b11110110110111001000010110 !
b11110110110111001000010110 .
1#
#2590500
0#
#2607000
b1111011011011100100001011011 *
b11 +
b111101101101110010000101101 !
b111101101101110010000101101 .
1#
#2623500
0#
#2640000
b11110110110111001000010110110 *
b10 +
b1111011011011100100001011011 !
b1111011011011100100001011011 .
1#
#2656500
0#
#2673000
b111101101101110010000101101101 *
b1 +
b11110110110111001000010110110 !
b11110110110111001000010110110 .
1#
#2689500
0#
#2706000
b1111011011011100100001011011011 *
b0 +
b111101101101110010000101101101 !
b111101101101110010000101101101 .
1#
#2722500
0#
#2739000
1'
b1010111010110100111100110111010 %
b1010111010110100111100110111010 (
b1110001110011110010111111010000 $
b1110001110011110010111111010000 )
1"
b1110000000110001001011001101010 *
b11111 +
0/
b111000000011000100101100110101 !
b111000000011000100101100110101 .
1#
#2755500
0#
#2772000
0'
b0 *
0"
b0 !
b0 .
b1010111010110100111100110111010 -
b1110001110011110010111111010000 ,
1/
1#
#2788500
0#
#2805000
b1 *
b11110 +
1#
#2821500
0#
#2838000
b11 *
b11101 +
b1 !
b1 .
1#
#2854500
0#
#2871000
b111 *
b11100 +
b11 !
b11 .
1#
#2887500
0#
#2904000
b1110 *
b11011 +
b111 !
b111 .
1#
#2920500
0#
#2937000
b11100 *
b11010 +
b1110 !
b1110 .
1#
#2953500
0#
#2970000
b111000 *
b11001 +
b11100 !
b11100 .
1#
#2986500
0#
#3003000
b1110001 *
b11000 +
b111000 !
b111000 .
1#
#3019500
0#
#3036000
b11100011 *
b10111 +
b1110001 !
b1110001 .
1#
#3052500
0#
#3069000
b111000111 *
b10110 +
b11100011 !
b11100011 .
1#
#3085500
0#
#3102000
b1110001110 *
b10101 +
b111000111 !
b111000111 .
1#
#3118500
0#
#3135000
b11100011100 *
b10100 +
b1110001110 !
b1110001110 .
1#
#3151500
0#
#3168000
b111000111001 *
b10011 +
b11100011100 !
b11100011100 .
1#
#3184500
0#
#3201000
b1110001110011 *
b10010 +
b111000111001 !
b111000111001 .
1#
#3217500
0#
#3234000
b11100011100111 *
b10001 +
b1110001110011 !
b1110001110011 .
1#
#3250500
0#
#3267000
b111000111001111 *
b10000 +
b11100011100111 !
b11100011100111 .
1#
#3283500
0#
#3300000
b1110001110011110 *
b1111 +
b111000111001111 !
b111000111001111 .
1#
#3316500
0#
#3333000
b11100011100111100 *
b1110 +
b1110001110011110 !
b1110001110011110 .
1#
#3349500
0#
#3366000
b111000111001111001 *
b1101 +
b11100011100111100 !
b11100011100111100 .
1#
#3382500
0#
#3399000
b1110001110011110010 *
b1100 +
b111000111001111001 !
b111000111001111001 .
1#
#3415500
0#
#3432000
b11100011100111100101 *
b1011 +
b1110001110011110010 !
b1110001110011110010 .
1#
#3448500
0#
#3465000
b111000111001111001011 *
b1010 +
b11100011100111100101 !
b11100011100111100101 .
1#
#3481500
0#
#3498000
b1110001110011110010111 *
b1001 +
b111000111001111001011 !
b111000111001111001011 .
1#
#3514500
0#
#3531000
b11100011100111100101111 *
b1000 +
b1110001110011110010111 !
b1110001110011110010111 .
1#
#3547500
0#
#3564000
b111000111001111001011111 *
b111 +
b11100011100111100101111 !
b11100011100111100101111 .
1#
#3580500
0#
#3597000
b1110001110011110010111111 *
b110 +
b111000111001111001011111 !
b111000111001111001011111 .
1#
#3613500
0#
#3630000
b11100011100111100101111110 *
b101 +
b1110001110011110010111111 !
b1110001110011110010111111 .
1#
#3646500
0#
#3663000
b111000111001111001011111101 *
b100 +
b11100011100111100101111110 !
b11100011100111100101111110 .
1#
#3679500
0#
#3696000
b1110001110011110010111111010 *
b11 +
b111000111001111001011111101 !
b111000111001111001011111101 .
1#
#3712500
0#
#3729000
b11100011100111100101111110100 *
b10 +
b1110001110011110010111111010 !
b1110001110011110010111111010 .
1#
#3745500
0#
#3762000
b111000111001111001011111101000 *
b1 +
b11100011100111100101111110100 !
b11100011100111100101111110100 .
1#
#3778500
0#
#3795000
b1110001110011110010111111010000 *
b0 +
b111000111001111001011111101000 !
b111000111001111001011111101000 .
1#
#3811500
0#
#3828000
1'
b11001000100011111110001111000 %
b11001000100011111110001111000 (
b1111110101011010010111011101101 $
b1111110101011010010111011101101 )
1"
b110100111010010110110000101100 *
b11111 +
0/
b11010011101001011011000010110 !
b11010011101001011011000010110 .
1#
#3844500
0#
#3861000
0'
b0 *
0"
b0 !
b0 .
b11001000100011111110001111000 -
b1111110101011010010111011101101 ,
1/
1#
#3877500
0#
#3894000
b1 *
b11110 +
1#
#3910500
0#
#3927000
b11 *
b11101 +
b1 !
b1 .
1#
#3943500
0#
#3960000
b111 *
b11100 +
b11 !
b11 .
1#
#3976500
0#
#3993000
b1111 *
b11011 +
b111 !
b111 .
1#
#4009500
0#
#4026000
b11111 *
b11010 +
b1111 !
b1111 .
1#
#4042500
0#
#4059000
b111111 *
b11001 +
b11111 !
b11111 .
1#
#4075500
0#
#4092000
b1111110 *
b11000 +
b111111 !
b111111 .
1#
#4108500
0#
#4125000
b11111101 *
b10111 +
b1111110 !
b1111110 .
1#
#4141500
0#
#4158000
b111111010 *
b10110 +
b11111101 !
b11111101 .
1#
#4174500
0#
#4191000
b1111110101 *
b10101 +
b111111010 !
b111111010 .
1#
#4207500
0#
#4224000
b11111101010 *
b10100 +
b1111110101 !
b1111110101 .
1#
#4240500
0#
#4257000
b111111010101 *
b10011 +
b11111101010 !
b11111101010 .
1#
#4273500
0#
#4290000
b1111110101011 *
b10010 +
b111111010101 !
b111111010101 .
1#
#4306500
0#
#4323000
b11111101010110 *
b10001 +
b1111110101011 !
b1111110101011 .
1#
#4339500
0#
#4356000
b111111010101101 *
b10000 +
b11111101010110 !
b11111101010110 .
1#
#4372500
0#
#4389000
b1111110101011010 *
b1111 +
b111111010101101 !
b111111010101101 .
1#
#4405500
0#
#4422000
b11111101010110100 *
b1110 +
b1111110101011010 !
b1111110101011010 .
1#
#4438500
0#
#4455000
b111111010101101001 *
b1101 +
b11111101010110100 !
b11111101010110100 .
1#
#4471500
0#
#4488000
b1111110101011010010 *
b1100 +
b111111010101101001 !
b111111010101101001 .
1#
#4504500
0#
#4521000
b11111101010110100101 *
b1011 +
b1111110101011010010 !
b1111110101011010010 .
1#
#4537500
0#
#4554000
b111111010101101001011 *
b1010 +
b11111101010110100101 !
b11111101010110100101 .
1#
#4570500
0#
#4587000
b1111110101011010010111 *
b1001 +
b111111010101101001011 !
b111111010101101001011 .
1#
#4603500
0#
#4620000
b11111101010110100101110 *
b1000 +
b1111110101011010010111 !
b1111110101011010010111 .
1#
#4636500
0#
#4653000
b111111010101101001011101 *
b111 +
b11111101010110100101110 !
b11111101010110100101110 .
1#
#4669500
0#
#4686000
b1111110101011010010111011 *
b110 +
b111111010101101001011101 !
b111111010101101001011101 .
1#
#4702500
0#
#4719000
b11111101010110100101110111 *
b101 +
b1111110101011010010111011 !
b1111110101011010010111011 .
1#
#4735500
0#
#4752000
b111111010101101001011101110 *
b100 +
b11111101010110100101110111 !
b11111101010110100101110111 .
1#
#4768500
0#
#4785000
b1111110101011010010111011101 *
b11 +
b111111010101101001011101110 !
b111111010101101001011101110 .
1#
#4801500
0#
#4818000
b11111101010110100101110111011 *
b10 +
b1111110101011010010111011101 !
b1111110101011010010111011101 .
1#
#4834500
0#
#4851000
b1101001100101001111010000110 *
b1 +
b110100110010100111101000011 !
b110100110010100111101000011 .
1#
#4867500
0#
#4884000
b11010011001010011110100001101 *
b0 +
b1101001100101001111010000110 !
b1101001100101001111010000110 .
1#
#4900500
0#
#4917000
1'
b1111001100011001100000010110111 %
b1111001100011001100000010110111 (
b1011110001100110010100000110001 $
b1011110001100110010100000110001 )
1"
b10101001101000000100101010 *
b11111 +
0/
b1010100110100000010010101 !
b1010100110100000010010101 .
1#
#4933500
0#
#4950000
0'
b0 *
0"
b0 !
b0 .
b1111001100011001100000010110111 -
b1011110001100110010100000110001 ,
1/
1#
#4966500
0#
#4983000
b1 *
b11110 +
1#
#4999500
0#
#5016000
b10 *
b11101 +
b1 !
b1 .
1#
#5032500
0#
#5049000
b101 *
b11100 +
b10 !
b10 .
1#
#5065500
0#
#5082000
b1011 *
b11011 +
b101 !
b101 .
1#
#5098500
0#
#5115000
b10111 *
b11010 +
b1011 !
b1011 .
1#
#5131500
0#
#5148000
b101111 *
b11001 +
b10111 !
b10111 .
1#
#5164500
0#
#5181000
b1011110 *
b11000 +
b101111 !
b101111 .
1#
#5197500
0#
#5214000
b10111100 *
b10111 +
b1011110 !
b1011110 .
1#
#5230500
0#
#5247000
b101111000 *
b10110 +
b10111100 !
b10111100 .
1#
#5263500
0#
#5280000
b1011110001 *
b10101 +
b101111000 !
b101111000 .
1#
#5296500
0#
#5313000
b10111100011 *
b10100 +
b1011110001 !
b1011110001 .
1#
#5329500
0#
#5346000
b101111000110 *
b10011 +
b10111100011 !
b10111100011 .
1#
#5362500
0#
#5379000
b1011110001100 *
b10010 +
b101111000110 !
b101111000110 .
1#
#5395500
0#
#5412000
b10111100011001 *
b10001 +
b1011110001100 !
b1011110001100 .
1#
#5428500
0#
#5445000
b101111000110011 *
b10000 +
b10111100011001 !
b10111100011001 .
1#
#5461500
0#
#5478000
b1011110001100110 *
b1111 +
b101111000110011 !
b101111000110011 .
1#
#5494500
0#
#5511000
b10111100011001100 *
b1110 +
b1011110001100110 !
b1011110001100110 .
1#
#5527500
0#
#5544000
b101111000110011001 *
b1101 +
b10111100011001100 !
b10111100011001100 .
1#
#5560500
0#
#5577000
b1011110001100110010 *
b1100 +
b101111000110011001 !
b101111000110011001 .
1#
#5593500
0#
#5610000
b10111100011001100101 *
b1011 +
b1011110001100110010 !
b1011110001100110010 .
1#
#5626500
0#
#5643000
b101111000110011001010 *
b1010 +
b10111100011001100101 !
b10111100011001100101 .
1#
#5659500
0#
#5676000
b1011110001100110010100 *
b1001 +
b101111000110011001010 !
b101111000110011001010 .
1#
#5692500
0#
#5709000
b10111100011001100101000 *
b1000 +
b1011110001100110010100 !
b1011110001100110010100 .
1#
#5725500
0#
#5742000
b101111000110011001010000 *
b111 +
b10111100011001100101000 !
b10111100011001100101000 .
1#
#5758500
0#
#5775000
b1011110001100110010100000 *
b110 +
b101111000110011001010000 !
b101111000110011001010000 .
1#
#5791500
0#
#5808000
b10111100011001100101000001 *
b101 +
b1011110001100110010100000 !
b1011110001100110010100000 .
1#
#5824500
0#
#5841000
b101111000110011001010000011 *
b100 +
b10111100011001100101000001 !
b10111100011001100101000001 .
1#
#5857500
0#
#5874000
b1011110001100110010100000110 *
b11 +
b101111000110011001010000011 !
b101111000110011001010000011 .
1#
#5890500
0#
#5907000
b10111100011001100101000001100 *
b10 +
b1011110001100110010100000110 !
b1011110001100110010100000110 .
1#
#5923500
0#
#5940000
b101111000110011001010000011000 *
b1 +
b10111100011001100101000001100 !
b10111100011001100101000001100 .
1#
#5956500
0#
#5973000
b1011110001100110010100000110001 *
b0 +
b101111000110011001010000011000 !
b101111000110011001010000011000 .
1#
#5989500
0#
#6006000
1'
b1110010010101111111110000110011 %
b1110010010101111111110000110011 (
b1001100011101111011010100100111 $
b1001100011101111011010100100111 )
1"
b10111100011001100101000001100010 *
b11111 +
0/
b1011110001100110010100000110001 !
b1011110001100110010100000110001 .
1#
#6022500
0#
#6039000
0'
b0 *
0"
b0 !
b0 .
b1110010010101111111110000110011 -
b1001100011101111011010100100111 ,
1/
1#
#6055500
0#
#6072000
b1 *
b11110 +
1#
#6088500
0#
#6105000
b10 *
b11101 +
b1 !
b1 .
1#
#6121500
0#
#6138000
b100 *
b11100 +
b10 !
b10 .
1#
#6154500
0#
#6171000
b1001 *
b11011 +
b100 !
b100 .
1#
#6187500
0#
#6204000
b10011 *
b11010 +
b1001 !
b1001 .
1#
#6220500
0#
#6237000
b100110 *
b11001 +
b10011 !
b10011 .
1#
#6253500
0#
#6270000
b1001100 *
b11000 +
b100110 !
b100110 .
1#
#6286500
0#
#6303000
b10011000 *
b10111 +
b1001100 !
b1001100 .
1#
#6319500
0#
#6336000
b100110001 *
b10110 +
b10011000 !
b10011000 .
1#
#6352500
0#
#6369000
b1001100011 *
b10101 +
b100110001 !
b100110001 .
1#
#6385500
0#
#6402000
b10011000111 *
b10100 +
b1001100011 !
b1001100011 .
1#
#6418500
0#
#6435000
b100110001110 *
b10011 +
b10011000111 !
b10011000111 .
1#
#6451500
0#
#6468000
b1001100011101 *
b10010 +
b100110001110 !
b100110001110 .
1#
#6484500
0#
#6501000
b10011000111011 *
b10001 +
b1001100011101 !
b1001100011101 .
1#
#6517500
0#
#6534000
b100110001110111 *
b10000 +
b10011000111011 !
b10011000111011 .
1#
#6550500
0#
#6567000
b1001100011101111 *
b1111 +
b100110001110111 !
b100110001110111 .
1#
#6583500
0#
#6600000
b10011000111011110 *
b1110 +
b1001100011101111 !
b1001100011101111 .
1#
#6616500
0#
#6633000
b100110001110111101 *
b1101 +
b10011000111011110 !
b10011000111011110 .
1#
#6649500
0#
#6666000
b1001100011101111011 *
b1100 +
b100110001110111101 !
b100110001110111101 .
1#
#6682500
0#
#6699000
b10011000111011110110 *
b1011 +
b1001100011101111011 !
b1001100011101111011 .
1#
#6715500
0#
#6732000
b100110001110111101101 *
b1010 +
b10011000111011110110 !
b10011000111011110110 .
1#
#6748500
0#
#6765000
b1001100011101111011010 *
b1001 +
b100110001110111101101 !
b100110001110111101101 .
1#
#6781500
0#
#6798000
b10011000111011110110101 *
b1000 +
b1001100011101111011010 !
b1001100011101111011010 .
1#
#6814500
0#
#6831000
b100110001110111101101010 *
b111 +
b10011000111011110110101 !
b10011000111011110110101 .
1#
#6847500
0#
#6864000
b1001100011101111011010100 *
b110 +
b100110001110111101101010 !
b100110001110111101101010 .
1#
#6880500
0#
#6897000
b10011000111011110110101001 *
b101 +
b1001100011101111011010100 !
b1001100011101111011010100 .
1#
#6913500
0#
#6930000
b100110001110111101101010010 *
b100 +
b10011000111011110110101001 !
b10011000111011110110101001 .
1#
#6946500
0#
#6963000
b1001100011101111011010100100 *
b11 +
b100110001110111101101010010 !
b100110001110111101101010010 .
1#
#6979500
0#
#6996000
b10011000111011110110101001001 *
b10 +
b1001100011101111011010100100 !
b1001100011101111011010100100 .
1#
#7012500
0#
#7029000
b100110001110111101101010010011 *
b1 +
b10011000111011110110101001001 !
b10011000111011110110101001001 .
1#
#7045500
0#
#7062000
b1001100011101111011010100100111 *
b0 +
b100110001110111101101010010011 !
b100110001110111101101010010011 .
1#
#7078500
0#
#7095000
1'
b1101011001101000010111010101101 %
b1101011001101000010111010101101 (
b111000000001000011100010010 $
b111000000001000011100010010 )
1"
b10011000111011110110101001001110 *
b11111 +
0/
b1001100011101111011010100100111 !
b1001100011101111011010100100111 .
1#
#7111500
0#
#7128000
0'
b0 *
0"
b0 !
b0 .
b1101011001101000010111010101101 -
b111000000001000011100010010 ,
1/
1#
#7144500
0#
#7161000
b11110 +
1#
#7177500
0#
#7194000
b11101 +
1#
#7210500
0#
#7227000
b11100 +
1#
#7243500
0#
#7260000
b11011 +
1#
#7276500
0#
#7293000
b1 *
b11010 +
1#
#7309500
0#
#7326000
b11 *
b11001 +
b1 !
b1 .
1#
#7342500
0#
#7359000
b111 *
b11000 +
b11 !
b11 .
1#
#7375500
0#
#7392000
b1110 *
b10111 +
b111 !
b111 .
1#
#7408500
0#
#7425000
b11100 *
b10110 +
b1110 !
b1110 .
1#
#7441500
0#
#7458000
b111000 *
b10101 +
b11100 !
b11100 .
1#
#7474500
0#
#7491000
b1110000 *
b10100 +
b111000 !
b111000 .
1#
#7507500
0#
#7524000
b11100000 *
b10011 +
b1110000 !
b1110000 .
1#
#7540500
0#
#7557000
b111000000 *
b10010 +
b11100000 !
b11100000 .
1#
#7573500
0#
#7590000
b1110000000 *
b10001 +
b111000000 !
b111000000 .
1#
#7606500
0#
#7623000
b11100000000 *
b10000 +
b1110000000 !
b1110000000 .
1#
#7639500
0#
#7656000
b111000000001 *
b1111 +
b11100000000 !
b11100000000 .
1#
#7672500
0#
#7689000
b1110000000010 *
b1110 +
b111000000001 !
b111000000001 .
1#
#7705500
0#
#7722000
b11100000000100 *
b1101 +
b1110000000010 !
b1110000000010 .
1#
#7738500
0#
#7755000
b111000000001000 *
b1100 +
b11100000000100 !
b11100000000100 .
1#
#7771500
0#
#7788000
b1110000000010000 *
b1011 +
b111000000001000 !
b111000000001000 .
1#
#7804500
0#
#7821000
b11100000000100001 *
b1010 +
b1110000000010000 !
b1110000000010000 .
1#
#7837500
0#
#7854000
b111000000001000011 *
b1001 +
b11100000000100001 !
b11100000000100001 .
1#
#7870500
0#
#7887000
b1110000000010000111 *
b1000 +
b111000000001000011 !
b111000000001000011 .
1#
#7903500
0#
#7920000
b11100000000100001110 *
b111 +
b1110000000010000111 !
b1110000000010000111 .
1#
#7936500
0#
#7953000
b111000000001000011100 *
b110 +
b11100000000100001110 !
b11100000000100001110 .
1#
#7969500
0#
#7986000
b1110000000010000111000 *
b101 +
b111000000001000011100 !
b111000000001000011100 .
1#
#8002500
0#
#8019000
b11100000000100001110001 *
b100 +
b1110000000010000111000 !
b1110000000010000111000 .
1#
#8035500
0#
#8052000
b111000000001000011100010 *
b11 +
b11100000000100001110001 !
b11100000000100001110001 .
1#
#8068500
0#
#8085000
b1110000000010000111000100 *
b10 +
b111000000001000011100010 !
b111000000001000011100010 .
1#
#8101500
0#
#8118000
b11100000000100001110001001 *
b1 +
b1110000000010000111000100 !
b1110000000010000111000100 .
1#
#8134500
0#
#8151000
b111000000001000011100010010 *
b0 +
b11100000000100001110001001 !
b11100000000100001110001001 .
1#
#8167500
0#
#8184000
1'
b1011001010001000000010110001101 %
b1011001010001000000010110001101 (
b1000111101010101000100101011111 $
b1000111101010101000100101011111 )
1"
b1110000000010000111000100100 *
b11111 +
0/
b111000000001000011100010010 !
b111000000001000011100010010 .
1#
#8200500
0#
#8217000
0'
b0 *
0"
b0 !
b0 .
b1011001010001000000010110001101 -
b1000111101010101000100101011111 ,
1/
1#
#8233500
0#
#8250000
b1 *
b11110 +
1#
#8266500
0#
#8283000
b10 *
b11101 +
b1 !
b1 .
1#
#8299500
0#
#8316000
b100 *
b11100 +
b10 !
b10 .
1#
#8332500
0#
#8349000
b1000 *
b11011 +
b100 !
b100 .
1#
#8365500
0#
#8382000
b10001 *
b11010 +
b1000 !
b1000 .
1#
#8398500
0#
#8415000
b100011 *
b11001 +
b10001 !
b10001 .
1#
#8431500
0#
#8448000
b1000111 *
b11000 +
b100011 !
b100011 .
1#
#8464500
0#
#8481000
b10001111 *
b10111 +
b1000111 !
b1000111 .
1#
#8497500
0#
#8514000
b100011110 *
b10110 +
b10001111 !
b10001111 .
1#
#8530500
0#
#8547000
b1000111101 *
b10101 +
b100011110 !
b100011110 .
1#
#8563500
0#
#8580000
b10001111010 *
b10100 +
b1000111101 !
b1000111101 .
1#
#8596500
0#
#8613000
b100011110101 *
b10011 +
b10001111010 !
b10001111010 .
1#
#8629500
0#
#8646000
b1000111101010 *
b10010 +
b100011110101 !
b100011110101 .
1#
#8662500
0#
#8679000
b10001111010101 *
b10001 +
b1000111101010 !
b1000111101010 .
1#
#8695500
0#
#8712000
b100011110101010 *
b10000 +
b10001111010101 !
b10001111010101 .
1#
#8728500
0#
#8745000
b1000111101010101 *
b1111 +
b100011110101010 !
b100011110101010 .
1#
#8761500
0#
#8778000
b10001111010101010 *
b1110 +
b1000111101010101 !
b1000111101010101 .
1#
#8794500
0#
#8811000
b100011110101010100 *
b1101 +
b10001111010101010 !
b10001111010101010 .
1#
#8827500
0#
#8844000
b1000111101010101000 *
b1100 +
b100011110101010100 !
b100011110101010100 .
1#
#8860500
0#
#8877000
b10001111010101010001 *
b1011 +
b1000111101010101000 !
b1000111101010101000 .
1#
#8893500
0#
#8910000
b100011110101010100010 *
b1010 +
b10001111010101010001 !
b10001111010101010001 .
1#
#8926500
0#
#8943000
b1000111101010101000100 *
b1001 +
b100011110101010100010 !
b100011110101010100010 .
1#
#8959500
0#
#8976000
b10001111010101010001001 *
b1000 +
b1000111101010101000100 !
b1000111101010101000100 .
1#
#8992500
0#
#9009000
b100011110101010100010010 *
b111 +
b10001111010101010001001 !
b10001111010101010001001 .
1#
#9025500
0#
#9042000
b1000111101010101000100101 *
b110 +
b100011110101010100010010 !
b100011110101010100010010 .
1#
#9058500
0#
